Metadata-Version: 2.1
Name: pyhuajiguai
Version: 0.0.1
Summary: 滑稽怪永远的神!!!
Home-page: UNKNOWN
Author: pyhuaji
Author-email: 794322340@qq.com
License: UNKNOWN
Platform: UNKNOWN
Classifier: Programming Language :: Python :: 3
Classifier: License :: OSI Approved :: MIT License
Classifier: Operating System :: OS Independent
Requires-Python: >=3.7
License-File: LICENSE
